tempest.py
tempest_fmt-1.0.2.dist-info/licenses/LICENSE
tempest_fmt-1.0.2.dist-info/METADATA
tempest_fmt-1.0.2.dist-info/WHEEL
tempest_fmt-1.0.2.dist-info/top_level.txt
tempest_fmt-1.0.2.dist-info/RECORD
