Metadata-Version: 2.4
Name: tempest-fmt
Version: 1.0.2
Summary: A tiny language-independent text templater for python
Author: Alagyn
License-Expression: MIT
Project-URL: Repository, https://github.com/alagyn/tempest
Project-URL: Issues, https://github.com/alagyn/tempest/issues
Classifier: Development Status :: 4 - Beta
Classifier: Intended Audience :: Developers
Classifier: Topic :: Text Processing
Classifier: Typing :: Typed
License-File: LICENSE
Dynamic: license-file
